llm_cluster_optimizer/__init__.py
llm_cluster_optimizer/examples.py
llm_cluster_optimizer/llm_clusterer.py
llm_cluster_optimizer/util.py
llm_cluster_optimizer-1.0.4.dist-info/METADATA
llm_cluster_optimizer-1.0.4.dist-info/WHEEL
llm_cluster_optimizer-1.0.4.dist-info/licenses/LICENSE
llm_cluster_optimizer-1.0.4.dist-info/RECORD
