Metadata-Version: 2.3
Name: llm_cluster_optimizer
Version: 1.0.4
Summary: A drop-in replacement for sklearn clustering models, this package optimizes sklearn clusters using LLMs
Project-URL: Homepage, https://github.com/nsantacruz/LLMClusterOptimizer
Project-URL: Issues, https://github.com/nsantacruz/LLMClusterOptimizer/issues
Author-email: Noah Santacruz <noahssantacruz@gmail.com>
License: MIT License
License-File: LICENSE
Keywords: LLM,kmeans,text clustering
Classifier: License :: OSI Approved :: MIT License
Classifier: Operating System :: OS Independent
Classifier: Programming Language :: Python :: 3
Requires-Python: >=3.8
Requires-Dist: langchain-community
Requires-Dist: langchain-openai
Requires-Dist: numpy
Requires-Dist: scikit-learn
Requires-Dist: tqdm
